incawrapper/__init__.py
incawrapper/core/INCAFitData.py
incawrapper/core/INCAModel.py
incawrapper/core/INCAMonteCarloResults.py
incawrapper/core/INCAResults.py
incawrapper/core/INCAScript.py
incawrapper/core/INCAScript_writing.py
incawrapper/core/INCASimulation.py
incawrapper/core/__init__.py
incawrapper/core/dataschemas.py
incawrapper/core/load_matlab_file.py
incawrapper/core/run_inca.py
incawrapper/utils/__init__.py
incawrapper/utils/chemical_formula.py
incawrapper/utils/merge_reversible_reactions.py
incawrapper/utils/schema_overview.py
incawrapper/visualization/__init__.py
incawrapper/visualization/diagnositics.py
incawrapper/visualization/visualization.py
incawrapper-1.1.1.dist-info/LICENSE
incawrapper-1.1.1.dist-info/METADATA
incawrapper-1.1.1.dist-info/WHEEL
incawrapper-1.1.1.dist-info/top_level.txt
incawrapper-1.1.1.dist-info/RECORD
