Metadata-Version: 2.1
Name: incawrapper
Version: 1.1.1
Summary: General Repository for Omics Data Handling tools
Home-page: 
Author: AutoFlow, Matthias Mattonovich and Viktor Hesselberg-Thomsen
Author-email: vikhes@dtu.dk
License: MIT
Classifier: Programming Language :: Python :: 3
Classifier: License :: OSI Approved :: MIT License
Classifier: Operating System :: OS Independent
License-File: LICENSE
Requires-Dist: pandas
Requires-Dist: numpy
Requires-Dist: matplotlib
Requires-Dist: pandera
Requires-Dist: scipy
Requires-Dist: requests
Requires-Dist: altair
Provides-Extra: atommapping
Requires-Dist: cobra ; extra == 'atommapping'
Requires-Dist: RDKit ; extra == 'atommapping'
Requires-Dist: pymatgen ; extra == 'atommapping'
Requires-Dist: openjdk ; extra == 'atommapping'
Provides-Extra: develop
Requires-Dist: pytest ; extra == 'develop'
Requires-Dist: ipykernel ; extra == 'develop'
Requires-Dist: python-dotenv ; extra == 'develop'
Requires-Dist: openpyxl ; extra == 'develop'
Requires-Dist: sphinx ==3.4.3 ; extra == 'develop'
Requires-Dist: numpydoc >=1.1 ; extra == 'develop'
Requires-Dist: nb2plots >=0.6 ; extra == 'develop'
Requires-Dist: jinja2 <3.1.0 ; extra == 'develop'
Requires-Dist: nbsphinx ==0.9.1 ; extra == 'develop'
Requires-Dist: sphinx-material ; extra == 'develop'
Requires-Dist: sphinx-autoapi ; extra == 'develop'
Provides-Extra: matlab
Requires-Dist: matlabengine ; extra == 'matlab'
